get_code_b3/__init__.py
get_code_b3/dolar.py
get_code_b3/indice.py
get_code_b3-0.1.0.dist-info/METADATA
get_code_b3-0.1.0.dist-info/WHEEL
get_code_b3-0.1.0.dist-info/RECORD
